patchcomm/__init__.py
patchcomm/dataloader.py
patchcomm/data/__init__.py
patchcomm/data/PDEP-SE/__init__.py
patchcomm/data/PDEP-SE/SkE/__init__.py
patchcomm/evaluations/__init__.py
patchcomm/evaluations/KR2021/__init__.py
patchcomm/evaluations/KR2021/evaluate_ppattach_belinkov.py
patchcomm/evaluations/KR2021/evaluate_wsc273.py
patchcomm/models/__init__.py
patchcomm/models/conceptnet_queryer.py
patchcomm/models/coref_resolver.py
patchcomm/models/pp_attacher.py
patchcomm/models/retrogan_drd_queryer.py
patchcomm/models/sentence_parser.py
patchcomm/models/start_queryer.py
patchcomm/tests/__init__.py
patchcomm/tests/test_dependency_visualizer.py
patchcomm/tests/test_retrogan_drd_queryer.py
patchcomm/tests/test_sentence_parser.py
patchcomm/tests/test_start_queryer.py
patchcomm/visualizer/__init__.py
patchcomm/visualizer/dependency_parse_visualizer.py
patchcomm-1.0.5.dist-info/LICENSE
patchcomm-1.0.5.dist-info/METADATA
patchcomm-1.0.5.dist-info/WHEEL
patchcomm-1.0.5.dist-info/top_level.txt
patchcomm-1.0.5.dist-info/RECORD
