Metadata-Version: 2.1
Name: patchcomm
Version: 1.0.5
Summary: PatchComm: Using Large-Scale Commonsense Knowledge to Guide Syntactic Parsers
Home-page: https://github.com/YidaXin/patchcomm
Author: Yida Xin
Author-email: yxin@bu.edu
License: UNKNOWN
Project-URL: Bug Tracker, https://github.com/YidaXin/patchcomm/issues
Platform: UNKNOWN
Classifier: Programming Language :: Python :: 3
Classifier: License :: OSI Approved :: MIT License
Classifier: Operating System :: OS Independent
Requires-Python: ==3.7.x
License-File: LICENSE
